fmov/__init__.py
fmov/video.py
fmov-0.3.0.dist-info/LICENSE
fmov-0.3.0.dist-info/METADATA
fmov-0.3.0.dist-info/WHEEL
fmov-0.3.0.dist-info/RECORD
