Metadata-Version: 2.3
Name: fmov
Version: 0.3.0
Summary: A simple, optimized way to programmatically create video with python.
License: MIT
Author: Dylan DiBeneditto
Author-email: dibenedittod@gmail.com
Requires-Python: >=3.12
Classifier: License :: OSI Approved :: MIT License
Classifier: Programming Language :: Python :: 3
Classifier: Programming Language :: Python :: 3.12
Classifier: Programming Language :: Python :: 3.13
Requires-Dist: ffmpeg-python
Requires-Dist: numpy
Requires-Dist: pillow
